xontrib/clp.py
xontrib_clp-0.1.7.dist-info/LICENSE
xontrib_clp-0.1.7.dist-info/METADATA
xontrib_clp-0.1.7.dist-info/WHEEL
xontrib_clp-0.1.7.dist-info/top_level.txt
xontrib_clp-0.1.7.dist-info/RECORD
