Metadata-Version: 2.1
Name: xontrib-clp
Version: 0.1.7
Summary: Copy output to clipboard.
Author-email: anki-code <no@no.no>
License: MIT License
Project-URL: Homepage, https://github.com/anki-code/xontrib-clp
Project-URL: Documentation, https://github.com/anki-code/xontrib-clp/blob/master/README.md
Project-URL: Code, https://github.com/anki-code/xontrib-clp
Project-URL: Issue tracker, https://github.com/anki-code/xontrib-clp/issues
Platform: any
Classifier: Programming Language :: Python :: 3
Classifier: License :: OSI Approved :: MIT License
Classifier: Operating System :: OS Independent
Classifier: Topic :: System :: Shells
Classifier: Topic :: System :: System Shells
Classifier: Topic :: Terminals
Requires-Python: >=3.8
License-File: LICENSE
Requires-Dist: xonsh >=0.12.5
Requires-Dist: pyperclip
Provides-Extra: dev
Requires-Dist: pytest >=7.0 ; extra == 'dev'
